{
  "pages": [
    {
      "id": 0,
      "website": 0,
      "home": true,
      "url": "http://website0.com/"
    },
    {
      "id": 1,
      "website": 1,
      "home": true,
      "url": "http://website1.com/"
    },
    {
      "id": 2,
      "website": 2,
      "home": true,
      "url": "http://website2.com/"
    },
    {
      "id": 3,
      "website": 3,
      "home": true,
      "url": "http://apropose.com/"
    },
    {
      "id": 4,
      "website": 3,
      "home": false,
      "url": "http://apropose.com/about"
    },
    {
      "id": 5,
      "website": 3,
      "home": false,
      "url": "http://apropose.com/jobs"
    },
    {
      "id": 6,
      "website": 4,
      "home": true,
      "url": "http://google.com/"
    },
    {
      "id": 7,
      "website": 5,
      "home": true,
      "url": "http://yahoo.com/"
    },
    {
      "id": 8,
      "website": 6,
      "home": true,
      "url": "http://bbc.co.uk/"
    },
    {
      "id": 9,
      "website": 4,
      "home": false,
      "url": "http://mail.google.com/"
    },
    {
      "id": 10,
      "website": 4,
      "home": false,
      "url": "http://mail.google.com/signin"
    },
    {
      "id": 11,
      "website": 4,
      "home": false,
      "url": "http://search.google.com/"
    },
    {
      "id": 12,
      "website": 4,
      "home": false,
      "url": "http://code.google.com/"
    },
    {
      "id": 13,
      "website": 4,
      "home": false,
      "url": "http://code.google.com/labs/"
    }
  ]
}
